setup.cfg
setup.py
amtk/__init__.py
amtk.egg-info/PKG-INFO
amtk.egg-info/SOURCES.txt
amtk.egg-info/dependency_links.txt
amtk.egg-info/entry_points.txt
amtk.egg-info/requires.txt
amtk.egg-info/top_level.txt
amtk/apps/__init__.py
amtk/apps/merge.py
amtk/apps/play.py
amtk/apps/record.py
amtk/apps/test.py
amtk/utils/__init__.py
amtk/utils/builtins.py
amtk/utils/messages.py
amtk/utils/misc.py
amtk/utils/options.py
amtk/utils/test.py
amtk/utils/testcase.py
amtk/utils/time.py