Metadata-Version: 1.1
Name: amtk
Version: 0.3.0
Summary: 
